sem6ml/__init__.py
sem6ml/ex10g.py
sem6ml/ex10q.py
sem6ml/ex3.py
sem6ml/ex4.py
sem6ml/ex6.py
sem6ml/ex7.py
sem6ml/ex8.py
sem6ml/ex9.py
sem6ml-0.1.dist-info/METADATA
sem6ml-0.1.dist-info/WHEEL
sem6ml-0.1.dist-info/top_level.txt
sem6ml-0.1.dist-info/RECORD
