Metadata-Version: 2.4
Name: sem6ml
Version: 0.1
Summary: ML Lab Exercises Package
Author: Machine Learning
Requires-Python: >=3.6
Requires-Dist: scikit-learn
Dynamic: author
Dynamic: requires-dist
Dynamic: requires-python
Dynamic: summary
